glenda/__init__.py
glenda/scanner.py
glenda/model/__init__.py
glenda/model/scanner_status.py
glenda-0.2.1.dist-info/LICENSE
glenda-0.2.1.dist-info/METADATA
glenda-0.2.1.dist-info/WHEEL
glenda-0.2.1.dist-info/top_level.txt
glenda-0.2.1.dist-info/RECORD
