Metadata-Version: 2.1
Name: glenda
Version: 0.2.1
Summary: Some tools for glenda
Home-page: https://github.com/pudo/normality
Author: Dmitry Mukovkin
Author-email: mukovkin@yandex.ru
License: UNKNOWN
Platform: UNKNOWN
Classifier: Programming Language :: Python :: 3
Classifier: License :: OSI Approved :: MIT License
Classifier: Operating System :: OS Independent
Requires-Python: >=3.6
Requires-Dist: confluent-kafka (==0.9.4)
